parameters_validation/__init__.py
parameters_validation/builtin_validations.py
parameters_validation/parameter_validation_decorator.py
parameters_validation/validate_parameters_decorator.py
parameters_validation-1.1.5.dist-info/LICENSE
parameters_validation-1.1.5.dist-info/METADATA
parameters_validation-1.1.5.dist-info/WHEEL
parameters_validation-1.1.5.dist-info/top_level.txt
parameters_validation-1.1.5.dist-info/RECORD
